synthimpute/__init__.py
synthimpute/distance.py
synthimpute/rf_impute.py
synthimpute/synthesize.py
synthimpute/trees.py
synthimpute-0.1.dist-info/LICENSE
synthimpute-0.1.dist-info/METADATA
synthimpute-0.1.dist-info/WHEEL
synthimpute-0.1.dist-info/top_level.txt
synthimpute-0.1.dist-info/RECORD
