Metadata-Version: 2.1
Name: synthimpute
Version: 0.1
Summary: Python package for data synthesis and imputation using parametric and nonparametric methods, and evaluation of these methods.
Home-page: http://github.com/PSLmodels/synthimpute
Author: Max Ghenis
Author-email: mghenis@gmail.com
License: MIT
Platform: UNKNOWN
Requires-Dist: numpy
Requires-Dist: pandas
Requires-Dist: scikit-learn
Requires-Dist: statsmodels
Requires-Dist: scipy
